src/stochastic_multiplier.v
module stochastic_multiplier(
    input wire a,
    input wire b,
    output wire y
);

assign y = a & b;

endmodule

src/stochastic_bitstream.v
module stochastic_bitstream(

    input clk,
    input reset,

    input [7:0] magnitude,
    input [7:0] seed,

    output bit_out

);

reg [7:0] rnd;

initial rnd = 8'h1;

always @(posedge clk or posedge reset)
begin
    if(reset)
        rnd <= seed;
    else
        rnd <= {rnd[6:0], rnd[7]^rnd[5]^rnd[4]^rnd[3]};
end

assign bit_out = (rnd < magnitude);

endmodule

src/stochastic_vector_dot_product.v
module stochastic_vector_dot_product(

    input clk,
    input reset,

    input [7:0] a1_mag,
    input [7:0] a2_mag,
    input [7:0] a3_mag,
    input [7:0] a4_mag,

    input [7:0] b1_mag,
    input [7:0] b2_mag,
    input [7:0] b3_mag,
    input [7:0] b4_mag,

    output reg [15:0] result

);

initial result = 0;

wire a1,a2,a3,a4;
wire b1,b2,b3,b4;

stochastic_bitstream A1(.clk(clk),.reset(reset),.magnitude(a1_mag),.seed(8'd1),   .bit_out(a1));
stochastic_bitstream A2(.clk(clk),.reset(reset),.magnitude(a2_mag),.seed(8'd7),   .bit_out(a2));
stochastic_bitstream A3(.clk(clk),.reset(reset),.magnitude(a3_mag),.seed(8'd13),  .bit_out(a3));
stochastic_bitstream A4(.clk(clk),.reset(reset),.magnitude(a4_mag),.seed(8'd19),  .bit_out(a4));

stochastic_bitstream B1(.clk(clk),.reset(reset),.magnitude(b1_mag),.seed(8'd23),  .bit_out(b1));
stochastic_bitstream B2(.clk(clk),.reset(reset),.magnitude(b2_mag),.seed(8'd29),  .bit_out(b2));
stochastic_bitstream B3(.clk(clk),.reset(reset),.magnitude(b3_mag),.seed(8'd31),  .bit_out(b3));
stochastic_bitstream B4(.clk(clk),.reset(reset),.magnitude(b4_mag),.seed(8'd37),  .bit_out(b4));

wire m1,m2,m3,m4;

stochastic_multiplier M1(.a(a1),.b(b1),.y(m1));
stochastic_multiplier M2(.a(a2),.b(b2),.y(m2));
stochastic_multiplier M3(.a(a3),.b(b3),.y(m3));
stochastic_multiplier M4(.a(a4),.b(b4),.y(m4));

reg [7:0] warmup;

always @(posedge clk or posedge reset)
begin
    if(reset)
    begin
        result <= 0;
        warmup <= 0;
    end

    else
    begin
        warmup <= warmup + 1;

        if(warmup > 20)   // wait for streams to stabilize
            result <= result + m1 + m2 + m3 + m4;
    end
end

endmodule

src/stochastic_matrix_multiply.v
module stochastic_matrix_multiply(

    input clk,
    input reset,

    input [7:0] a11,a12,
    input [7:0] a21,a22,

    input [7:0] b11,b12,
    input [7:0] b21,b22,

    output [15:0] c11,
    output [15:0] c12,
    output [15:0] c21,
    output [15:0] c22

);

stochastic_vector_dot_product dp11(
    .clk(clk), .reset(reset),
    .a1_mag(a11), .a2_mag(a12), .a3_mag(8'd0), .a4_mag(8'd0),
    .b1_mag(b11), .b2_mag(b21), .b3_mag(8'd0), .b4_mag(8'd0),
    .result(c11)
);

stochastic_vector_dot_product dp12(
    .clk(clk), .reset(reset),
    .a1_mag(a11), .a2_mag(a12), .a3_mag(8'd0), .a4_mag(8'd0),
    .b1_mag(b12), .b2_mag(b22), .b3_mag(8'd0), .b4_mag(8'd0),
    .result(c12)
);

stochastic_vector_dot_product dp21(
    .clk(clk), .reset(reset),
    .a1_mag(a21), .a2_mag(a22), .a3_mag(8'd0), .a4_mag(8'd0),
    .b1_mag(b11), .b2_mag(b21), .b3_mag(8'd0), .b4_mag(8'd0),
    .result(c21)
);

stochastic_vector_dot_product dp22(
    .clk(clk), .reset(reset),
    .a1_mag(a21), .a2_mag(a22), .a3_mag(8'd0), .a4_mag(8'd0),
    .b1_mag(b12), .b2_mag(b22), .b3_mag(8'd0), .b4_mag(8'd0),
    .result(c22)
);

endmodule

tb/tb_stochastic_matrix_multiply.v
`timescale 1ns/1ps

module tb_stochastic_matrix_multiply;

reg clk;
reg reset;

reg [7:0] a11,a12,a21,a22;
reg [7:0] b11,b12,b21,b22;

wire [15:0] c11,c12,c21,c22;

stochastic_matrix_multiply uut(

    .clk(clk),
    .reset(reset),

    .a11(a11), .a12(a12),
    .a21(a21), .a22(a22),

    .b11(b11), .b12(b12),
    .b21(b21), .b22(b22),

    .c11(c11), .c12(c12),
    .c21(c21), .c22(c22)

);

initial begin
    clk=0;
    forever #5 clk = ~clk;
end

initial begin

$dumpfile("output/waveform.vcd");
$dumpvars(0,tb_stochastic_matrix_multiply);

reset=1;
#30;
reset=0;

/* Example matrices */

a11=8'd128;  //0.5
a12=8'd64;   //0.25
a21=8'd192;  //0.75
a22=8'd32;   //0.125

b11=8'd128;
b12=8'd64;
b21=8'd128;
b22=8'd64;

repeat(1000)
#10;

$display("C11=%d C12=%d C21=%d C22=%d",c11,c12,c21,c22);

$finish;

end

endmodule

output/waveform.vcd
$date
	Sat Mar 07 18:43:28 2026
$end
$version
	Icarus Verilog
$end
$timescale
	1ps
$end
$scope module tb_stochastic_matrix_multiply $end
$var wire 16 ! c22 [15:0] $end
$var wire 16 " c21 [15:0] $end
$var wire 16 # c12 [15:0] $end
$var wire 16 $ c11 [15:0] $end
$var reg 8 % a11 [7:0] $end
$var reg 8 & a12 [7:0] $end
$var reg 8 ' a21 [7:0] $end
$var reg 8 ( a22 [7:0] $end
$var reg 8 ) b11 [7:0] $end
$var reg 8 * b12 [7:0] $end
$var reg 8 + b21 [7:0] $end
$var reg 8 , b22 [7:0] $end
$var reg 1 - clk $end
$var reg 1 . reset $end
$scope module uut $end
$var wire 8 / a11 [7:0] $end
$var wire 8 0 a12 [7:0] $end
$var wire 8 1 a21 [7:0] $end
$var wire 8 2 a22 [7:0] $end
$var wire 8 3 b11 [7:0] $end
$var wire 8 4 b12 [7:0] $end
$var wire 8 5 b21 [7:0] $end
$var wire 8 6 b22 [7:0] $end
$var wire 1 - clk $end
$var wire 1 . reset $end
$var wire 16 7 c22 [15:0] $end
$var wire 16 8 c21 [15:0] $end
$var wire 16 9 c12 [15:0] $end
$var wire 16 : c11 [15:0] $end
$scope module dp11 $end
$var wire 8 ; a1_mag [7:0] $end
$var wire 8 < a2_mag [7:0] $end
$var wire 8 = a3_mag [7:0] $end
$var wire 8 > a4_mag [7:0] $end
$var wire 8 ? b1_mag [7:0] $end
$var wire 8 @ b2_mag [7:0] $end
$var wire 8 A b3_mag [7:0] $end
$var wire 8 B b4_mag [7:0] $end
$var wire 1 - clk $end
$var wire 1 . reset $end
$var wire 1 C m4 $end
$var wire 1 D m3 $end
$var wire 1 E m2 $end
$var wire 1 F m1 $end
$var wire 1 G b4 $end
$var wire 1 H b3 $end
$var wire 1 I b2 $end
$var wire 1 J b1 $end
$var wire 1 K a4 $end
$var wire 1 L a3 $end
$var wire 1 M a2 $end
$var wire 1 N a1 $end
$var reg 16 O result [15:0] $end
$var reg 8 P warmup [7:0] $end
$scope module A1 $end
$var wire 1 - clk $end
$var wire 8 Q magnitude [7:0] $end
$var wire 1 . reset $end
$var wire 8 R seed [7:0] $end
$var wire 1 N bit_out $end
$var reg 8 S rnd [7:0] $end
$upscope $end
$scope module A2 $end
$var wire 1 - clk $end
$var wire 8 T magnitude [7:0] $end
$var wire 1 . reset $end
$var wire 8 U seed [7:0] $end
$var wire 1 M bit_out $end
$var reg 8 V rnd [7:0] $end
$upscope $end
$scope module A3 $end
$var wire 1 - clk $end
$var wire 8 W magnitude [7:0] $end
$var wire 1 . reset $end
$var wire 8 X seed [7:0] $end
$var wire 1 L bit_out $end
$var reg 8 Y rnd [7:0] $end
$upscope $end
$scope module A4 $end
$var wire 1 - clk $end
$var wire 8 Z magnitude [7:0] $end
$var wire 1 . reset $end
$var wire 8 [ seed [7:0] $end
$var wire 1 K bit_out $end
$var reg 8 \ rnd [7:0] $end
$upscope $end
$scope module B1 $end
$var wire 1 - clk $end
$var wire 8 ] magnitude [7:0] $end
$var wire 1 . reset $end
$var wire 8 ^ seed [7:0] $end
$var wire 1 J bit_out $end
$var reg 8 _ rnd [7:0] $end
$upscope $end
$scope module B2 $end
$var wire 1 - clk $end
$var wire 8 ` magnitude [7:0] $end
$var wire 1 . reset $end
$var wire 8 a seed [7:0] $end
$var wire 1 I bit_out $end
$var reg 8 b rnd [7:0] $end
$upscope $end
$scope module B3 $end
$var wire 1 - clk $end
$var wire 8 c magnitude [7:0] $end
$var wire 1 . reset $end
$var wire 8 d seed [7:0] $end
$var wire 1 H bit_out $end
$var reg 8 e rnd [7:0] $end
$upscope $end
$scope module B4 $end
$var wire 1 - clk $end
$var wire 8 f magnitude [7:0] $end
$var wire 1 . reset $end
$var wire 8 g seed [7:0] $end
$var wire 1 G bit_out $end
$var reg 8 h rnd [7:0] $end
$upscope $end
$scope module M1 $end
$var wire 1 N a $end
$var wire 1 J b $end
$var wire 1 F y $end
$upscope $end
$scope module M2 $end
$var wire 1 M a $end
$var wire 1 I b $end
$var wire 1 E y $end
$upscope $end
$scope module M3 $end
$var wire 1 L a $end
$var wire 1 H b $end
$var wire 1 D y $end
$upscope $end
$scope module M4 $end
$var wire 1 K a $end
$var wire 1 G b $end
$var wire 1 C y $end
$upscope $end
$upscope $end
$scope module dp12 $end
$var wire 8 i a1_mag [7:0] $end
$var wire 8 j a2_mag [7:0] $end
$var wire 8 k a3_mag [7:0] $end
$var wire 8 l a4_mag [7:0] $end
$var wire 8 m b1_mag [7:0] $end
$var wire 8 n b2_mag [7:0] $end
$var wire 8 o b3_mag [7:0] $end
$var wire 8 p b4_mag [7:0] $end
$var wire 1 - clk $end
$var wire 1 . reset $end
$var wire 1 q m4 $end
$var wire 1 r m3 $end
$var wire 1 s m2 $end
$var wire 1 t m1 $end
$var wire 1 u b4 $end
$var wire 1 v b3 $end
$var wire 1 w b2 $end
$var wire 1 x b1 $end
$var wire 1 y a4 $end
$var wire 1 z a3 $end
$var wire 1 { a2 $end
$var wire 1 | a1 $end
$var reg 16 } result [15:0] $end
$var reg 8 ~ warmup [7:0] $end
$scope module A1 $end
$var wire 1 - clk $end
$var wire 8 !" magnitude [7:0] $end
$var wire 1 . reset $end
$var wire 8 "" seed [7:0] $end
$var wire 1 | bit_out $end
$var reg 8 #" rnd [7:0] $end
$upscope $end
$scope module A2 $end
$var wire 1 - clk $end
$var wire 8 $" magnitude [7:0] $end
$var wire 1 . reset $end
$var wire 8 %" seed [7:0] $end
$var wire 1 { bit_out $end
$var reg 8 &" rnd [7:0] $end
$upscope $end
$scope module A3 $end
$var wire 1 - clk $end
$var wire 8 '" magnitude [7:0] $end
$var wire 1 . reset $end
$var wire 8 (" seed [7:0] $end
$var wire 1 z bit_out $end
$var reg 8 )" rnd [7:0] $end
$upscope $end
$scope module A4 $end
$var wire 1 - clk $end
$var wire 8 *" magnitude [7:0] $end
$var wire 1 . reset $end
$var wire 8 +" seed [7:0] $end
$var wire 1 y bit_out $end
$var reg 8 ," rnd [7:0] $end
$upscope $end
$scope module B1 $end
$var wire 1 - clk $end
$var wire 8 -" magnitude [7:0] $end
$var wire 1 . reset $end
$var wire 8 ." seed [7:0] $end
$var wire 1 x bit_out $end
$var reg 8 /" rnd [7:0] $end
$upscope $end
$scope module B2 $end
$var wire 1 - clk $end
$var wire 8 0" magnitude [7:0] $end
$var wire 1 . reset $end
$var wire 8 1" seed [7:0] $end
$var wire 1 w bit_out $end
$var reg 8 2" rnd [7:0] $end
$upscope $end
$scope module B3 $end
$var wire 1 - clk $end
$var wire 8 3" magnitude [7:0] $end
$var wire 1 . reset $end
$var wire 8 4" seed [7:0] $end
$var wire 1 v bit_out $end
$var reg 8 5" rnd [7:0] $end
$upscope $end
$scope module B4 $end
$var wire 1 - clk $end
$var wire 8 6" magnitude [7:0] $end
$var wire 1 . reset $end
$var wire 8 7" seed [7:0] $end
$var wire 1 u bit_out $end
$var reg 8 8" rnd [7:0] $end
$upscope $end
$scope module M1 $end
$var wire 1 | a $end
$var wire 1 x b $end
$var wire 1 t y $end
$upscope $end
$scope module M2 $end
$var wire 1 { a $end
$var wire 1 w b $end
$var wire 1 s y $end
$upscope $end
$scope module M3 $end
$var wire 1 z a $end
$var wire 1 v b $end
$var wire 1 r y $end
$upscope $end
$scope module M4 $end
$var wire 1 y a $end
$var wire 1 u b $end
$var wire 1 q y $end
$upscope $end
$upscope $end
$scope module dp21 $end
$var wire 8 9" a1_mag [7:0] $end
$var wire 8 :" a2_mag [7:0] $end
$var wire 8 ;" a3_mag [7:0] $end
$var wire 8 <" a4_mag [7:0] $end
$var wire 8 =" b1_mag [7:0] $end
$var wire 8 >" b2_mag [7:0] $end
$var wire 8 ?" b3_mag [7:0] $end
$var wire 8 @" b4_mag [7:0] $end
$var wire 1 - clk $end
$var wire 1 . reset $end
$var wire 1 A" m4 $end
$var wire 1 B" m3 $end
$var wire 1 C" m2 $end
$var wire 1 D" m1 $end
$var wire 1 E" b4 $end
$var wire 1 F" b3 $end
$var wire 1 G" b2 $end
$var wire 1 H" b1 $end
$var wire 1 I" a4 $end
$var wire 1 J" a3 $end
$var wire 1 K" a2 $end
$var wire 1 L" a1 $end
$var reg 16 M" result [15:0] $end
$var reg 8 N" warmup [7:0] $end
$scope module A1 $end
$var wire 1 - clk $end
$var wire 8 O" magnitude [7:0] $end
$var wire 1 . reset $end
$var wire 8 P" seed [7:0] $end
$var wire 1 L" bit_out $end
$var reg 8 Q" rnd [7:0] $end
$upscope $end
$scope module A2 $end
$var wire 1 - clk $end
$var wire 8 R" magnitude [7:0] $end
$var wire 1 . reset $end
$var wire 8 S" seed [7:0] $end
$var wire 1 K" bit_out $end
$var reg 8 T" rnd [7:0] $end
$upscope $end
$scope module A3 $end
$var wire 1 - clk $end
$var wire 8 U" magnitude [7:0] $end
$var wire 1 . reset $end
$var wire 8 V" seed [7:0] $end
$var wire 1 J" bit_out $end
$var reg 8 W" rnd [7:0] $end
$upscope $end
$scope module A4 $end
$var wire 1 - clk $end
$var wire 8 X" magnitude [7:0] $end
$var wire 1 . reset $end
$var wire 8 Y" seed [7:0] $end
$var wire 1 I" bit_out $end
$var reg 8 Z" rnd [7:0] $end
$upscope $end
$scope module B1 $end
$var wire 1 - clk $end
$var wire 8 [" magnitude [7:0] $end
$var wire 1 . reset $end
$var wire 8 \" seed [7:0] $end
$var wire 1 H" bit_out $end
$var reg 8 ]" rnd [7:0] $end
$upscope $end
$scope module B2 $end
$var wire 1 - clk $end
$var wire 8 ^" magnitude [7:0] $end
$var wire 1 . reset $end
$var wire 8 _" seed [7:0] $end
$var wire 1 G" bit_out $end
$var reg 8 `" rnd [7:0] $end
$upscope $end
$scope module B3 $end
$var wire 1 - clk $end
$var wire 8 a" magnitude [7:0] $end
$var wire 1 . reset $end
$var wire 8 b" seed [7:0] $end
$var wire 1 F" bit_out $end
$var reg 8 c" rnd [7:0] $end
$upscope $end
$scope module B4 $end
$var wire 1 - clk $end
$var wire 8 d" magnitude [7:0] $end
$var wire 1 . reset $end
$var wire 8 e" seed [7:0] $end
$var wire 1 E" bit_out $end
$var reg 8 f" rnd [7:0] $end
$upscope $end
$scope module M1 $end
$var wire 1 L" a $end
$var wire 1 H" b $end
$var wire 1 D" y $end
$upscope $end
$scope module M2 $end
$var wire 1 K" a $end
$var wire 1 G" b $end
$var wire 1 C" y $end
$upscope $end
$scope module M3 $end
$var wire 1 J" a $end
$var wire 1 F" b $end
$var wire 1 B" y $end
$upscope $end
$scope module M4 $end
$var wire 1 I" a $end
$var wire 1 E" b $end
$var wire 1 A" y $end
$upscope $end
$upscope $end
$scope module dp22 $end
$var wire 8 g" a1_mag [7:0] $end
$var wire 8 h" a2_mag [7:0] $end
$var wire 8 i" a3_mag [7:0] $end
$var wire 8 j" a4_mag [7:0] $end
$var wire 8 k" b1_mag [7:0] $end
$var wire 8 l" b2_mag [7:0] $end
$var wire 8 m" b3_mag [7:0] $end
$var wire 8 n" b4_mag [7:0] $end
$var wire 1 - clk $end
$var wire 1 . reset $end
$var wire 1 o" m4 $end
$var wire 1 p" m3 $end
$var wire 1 q" m2 $end
$var wire 1 r" m1 $end
$var wire 1 s" b4 $end
$var wire 1 t" b3 $end
$var wire 1 u" b2 $end
$var wire 1 v" b1 $end
$var wire 1 w" a4 $end
$var wire 1 x" a3 $end
$var wire 1 y" a2 $end
$var wire 1 z" a1 $end
$var reg 16 {" result [15:0] $end
$var reg 8 |" warmup [7:0] $end
$scope module A1 $end
$var wire 1 - clk $end
$var wire 8 }" magnitude [7:0] $end
$var wire 1 . reset $end
$var wire 8 ~" seed [7:0] $end
$var wire 1 z" bit_out $end
$var reg 8 !# rnd [7:0] $end
$upscope $end
$scope module A2 $end
$var wire 1 - clk $end
$var wire 8 "# magnitude [7:0] $end
$var wire 1 . reset $end
$var wire 8 ## seed [7:0] $end
$var wire 1 y" bit_out $end
$var reg 8 $# rnd [7:0] $end
$upscope $end
$scope module A3 $end
$var wire 1 - clk $end
$var wire 8 %# magnitude [7:0] $end
$var wire 1 . reset $end
$var wire 8 &# seed [7:0] $end
$var wire 1 x" bit_out $end
$var reg 8 '# rnd [7:0] $end
$upscope $end
$scope module A4 $end
$var wire 1 - clk $end
$var wire 8 (# magnitude [7:0] $end
$var wire 1 . reset $end
$var wire 8 )# seed [7:0] $end
$var wire 1 w" bit_out $end
$var reg 8 *# rnd [7:0] $end
$upscope $end
$scope module B1 $end
$var wire 1 - clk $end
$var wire 8 +# magnitude [7:0] $end
$var wire 1 . reset $end
$var wire 8 ,# seed [7:0] $end
$var wire 1 v" bit_out $end
$var reg 8 -# rnd [7:0] $end
$upscope $end
$scope module B2 $end
$var wire 1 - clk $end
$var wire 8 .# magnitude [7:0] $end
$var wire 1 . reset $end
$var wire 8 /# seed [7:0] $end
$var wire 1 u" bit_out $end
$var reg 8 0# rnd [7:0] $end
$upscope $end
$scope module B3 $end
$var wire 1 - clk $end
$var wire 8 1# magnitude [7:0] $end
$var wire 1 . reset $end
$var wire 8 2# seed [7:0] $end
$var wire 1 t" bit_out $end
$var reg 8 3# rnd [7:0] $end
$upscope $end
$scope module B4 $end
$var wire 1 - clk $end
$var wire 8 4# magnitude [7:0] $end
$var wire 1 . reset $end
$var wire 8 5# seed [7:0] $end
$var wire 1 s" bit_out $end
$var reg 8 6# rnd [7:0] $end
$upscope $end
$scope module M1 $end
$var wire 1 z" a $end
$var wire 1 v" b $end
$var wire 1 r" y $end
$upscope $end
$scope module M2 $end
$var wire 1 y" a $end
$var wire 1 u" b $end
$var wire 1 q" y $end
$upscope $end
$scope module M3 $end
$var wire 1 x" a $end
$var wire 1 t" b $end
$var wire 1 p" y $end
$upscope $end
$scope module M4 $end
$var wire 1 w" a $end
$var wire 1 s" b $end
$var wire 1 o" y $end
$upscope $end
$upscope $end
$upscope $end
$upscope $end
$enddefinitions $end
#0
$dumpvars
b100101 6#
b100101 5#
b0 4#
b11111 3#
b11111 2#
b0 1#
b11101 0#
b11101 /#
bx .#
b10111 -#
b10111 ,#
bx +#
b10011 *#
b10011 )#
b0 (#
b1101 '#
b1101 &#
b0 %#
b111 $#
b111 ##
bx "#
b1 !#
b1 ~"
bx }"
b0 |"
b0 {"
xz"
xy"
0x"
0w"
xv"
xu"
0t"
0s"
xr"
xq"
0p"
0o"
b0 n"
b0 m"
bx l"
bx k"
b0 j"
b0 i"
bx h"
bx g"
b100101 f"
b100101 e"
b0 d"
b11111 c"
b11111 b"
b0 a"
b11101 `"
b11101 _"
bx ^"
b10111 ]"
b10111 \"
bx ["
b10011 Z"
b10011 Y"
b0 X"
b1101 W"
b1101 V"
b0 U"
b111 T"
b111 S"
bx R"
b1 Q"
b1 P"
bx O"
b0 N"
b0 M"
xL"
xK"
0J"
0I"
xH"
xG"
0F"
0E"
xD"
xC"
0B"
0A"
b0 @"
b0 ?"
bx >"
bx ="
b0 <"
b0 ;"
bx :"
bx 9"
b100101 8"
b100101 7"
b0 6"
b11111 5"
b11111 4"
b0 3"
b11101 2"
b11101 1"
bx 0"
b10111 /"
b10111 ."
bx -"
b10011 ,"
b10011 +"
b0 *"
b1101 )"
b1101 ("
b0 '"
b111 &"
b111 %"
bx $"
b1 #"
b1 ""
bx !"
b0 ~
b0 }
x|
x{
0z
0y
xx
xw
0v
0u
xt
xs
0r
0q
b0 p
b0 o
bx n
bx m
b0 l
b0 k
bx j
bx i
b100101 h
b100101 g
b0 f
b11111 e
b11111 d
b0 c
b11101 b
b11101 a
bx `
b10111 _
b10111 ^
bx ]
b10011 \
b10011 [
b0 Z
b1101 Y
b1101 X
b0 W
b111 V
b111 U
bx T
b1 S
b1 R
bx Q
b0 P
b0 O
xN
xM
0L
0K
xJ
xI
0H
0G
xF
xE
0D
0C
b0 B
b0 A
bx @
bx ?
b0 >
b0 =
bx <
bx ;
b0 :
b0 9
b0 8
b0 7
bx 6
bx 5
bx 4
bx 3
bx 2
bx 1
bx 0
bx /
1.
0-
bx ,
bx +
bx *
bx )
bx (
bx '
bx &
bx %
b0 $
b0 #
b0 "
b0 !
$end
#5000
1-
#10000
0-
#15000
1-
#20000
0-
#25000
1-
#30000
1C"
1q"
1D"
1r"
1E
1s
1F
1t
0-
1w
1u"
b1000000 ,
b1000000 6
b1000000 n
b1000000 0"
b1000000 l"
b1000000 .#
1I
1G"
b10000000 +
b10000000 5
b10000000 @
b10000000 `
b10000000 >"
b10000000 ^"
1x
1v"
b1000000 *
b1000000 4
b1000000 m
b1000000 -"
b1000000 k"
b1000000 +#
1J
1H"
b10000000 )
b10000000 3
b10000000 ?
b10000000 ]
b10000000 ="
b10000000 ["
1K"
1y"
b100000 (
b100000 2
b100000 :"
b100000 R"
b100000 h"
b100000 "#
1L"
1z"
b11000000 '
b11000000 1
b11000000 9"
b11000000 O"
b11000000 g"
b11000000 }"
1M
1{
b1000000 &
b1000000 0
b1000000 <
b1000000 T
b1000000 j
b1000000 $"
1N
1|
b10000000 %
b10000000 /
b10000000 ;
b10000000 Q
b10000000 i
b10000000 !"
0.
#35000
b10 S
b1110 V
b11011 Y
b100111 \
b101111 _
b111010 b
b111110 e
b1001011 h
b1 P
b10 #"
b1110 &"
b11011 )"
b100111 ,"
b101111 /"
b111010 2"
b111110 5"
b1001011 8"
b1 ~
b10 Q"
b1110 T"
b11011 W"
b100111 Z"
b101111 ]"
b111010 `"
b111110 c"
b1001011 f"
b1 N"
b10 !#
b1110 $#
b11011 '#
b100111 *#
b101111 -#
b111010 0#
b111110 3#
b1001011 6#
b1 |"
1-
#40000
0-
#45000
0q"
0r"
0s
0t
b10 |"
b10010111 6#
b1111101 3#
0u"
b1110101 0#
0v"
b1011110 -#
b1001111 *#
b110110 '#
b11101 $#
b100 !#
b10 N"
b10010111 f"
b1111101 c"
b1110101 `"
b1011110 ]"
b1001111 Z"
b110110 W"
b11101 T"
b100 Q"
b10 ~
b10010111 8"
b1111101 5"
0w
b1110101 2"
0x
b1011110 /"
b1001111 ,"
b110110 )"
b11101 &"
b100 #"
b10 P
b10010111 h
b1111101 e
b1110101 b
b1011110 _
b1001111 \
b110110 Y
b11101 V
b100 S
1-
#50000
0-
#55000
0F
0E
0D"
0C"
b1000 S
b111010 V
b1101100 Y
b10011111 \
0J
b10111100 _
0I
b11101010 b
b11111011 e
b101110 h
b11 P
b1000 #"
b111010 &"
b1101100 )"
b10011111 ,"
b10111100 /"
b11101010 2"
b11111011 5"
b101110 8"
b11 ~
b1000 Q"
0K"
b111010 T"
b1101100 W"
b10011111 Z"
0H"
b10111100 ]"
0G"
b11101010 `"
b11111011 c"
b101110 f"
b11 N"
b1000 !#
0y"
b111010 $#
b1101100 '#
b10011111 *#
b10111100 -#
b11101010 0#
b11111011 3#
b101110 6#
b11 |"
1-
#60000
0-
#65000
1D"
1F
b100 |"
b1011100 6#
b11110110 3#
b11010101 0#
b1111000 -#
b111111 *#
b11011000 '#
b1110101 $#
b10001 !#
b100 N"
b1011100 f"
b11110110 c"
b11010101 `"
1H"
b1111000 ]"
b111111 Z"
b11011000 W"
b1110101 T"
b10001 Q"
b100 ~
b1011100 8"
b11110110 5"
b11010101 2"
b1111000 /"
b111111 ,"
b11011000 )"
0{
b1110101 &"
b10001 #"
b100 P
b1011100 h
b11110110 e
b11010101 b
1J
b1111000 _
b111111 \
b11011000 Y
0M
b1110101 V
b10001 S
1-
#70000
0-
#75000
0F
0D"
b100011 S
b11101010 V
b10110001 Y
b1111111 \
0J
b11110001 _
b10101010 b
b11101101 e
b10111000 h
b101 P
b100011 #"
b11101010 &"
b10110001 )"
b1111111 ,"
b11110001 /"
b10101010 2"
b11101101 5"
b10111000 8"
b101 ~
b100011 Q"
b11101010 T"
b10110001 W"
b1111111 Z"
0H"
b11110001 ]"
b10101010 `"
b11101101 c"
b10111000 f"
b101 N"
b100011 !#
b11101010 $#
b10110001 '#
b1111111 *#
b11110001 -#
b10101010 0#
b11101101 3#
b10111000 6#
b101 |"
1-
#80000
0-
#85000
b110 |"
b1110000 6#
b11011011 3#
b1010101 0#
b11100011 -#
b11111111 *#
b1100011 '#
b11010101 $#
b1000111 !#
b110 N"
b1110000 f"
b11011011 c"
1G"
b1010101 `"
b11100011 ]"
b11111111 Z"
b1100011 W"
b11010101 T"
b1000111 Q"
b110 ~
b1110000 8"
b11011011 5"
b1010101 2"
b11100011 /"
b11111111 ,"
b1100011 )"
b11010101 &"
b1000111 #"
b110 P
b1110000 h
b11011011 e
1I
b1010101 b
b11100011 _
b11111111 \
b1100011 Y
b11010101 V
b1000111 S
1-
#90000
0-
#95000
0N
b10001110 S
b10101010 V
b11000111 Y
b11111110 \
b11000110 _
0I
b10101011 b
b10110111 e
b11100000 h
b111 P
0|
b10001110 #"
b10101010 &"
b11000111 )"
b11111110 ,"
b11000110 /"
b10101011 2"
b10110111 5"
b11100000 8"
b111 ~
b10001110 Q"
b10101010 T"
b11000111 W"
b11111110 Z"
b11000110 ]"
0G"
b10101011 `"
b10110111 c"
b11100000 f"
b111 N"
b10001110 !#
b10101010 $#
b11000111 '#
b11111110 *#
b11000110 -#
b10101011 0#
b10110111 3#
b11100000 6#
b111 |"
1-
#100000
0-
#105000
b1000 |"
b11000000 6#
b1101111 3#
b1010111 0#
b10001101 -#
b11111100 *#
b10001111 '#
b1010101 $#
b11100 !#
b1000 N"
b11000000 f"
b1101111 c"
1G"
b1010111 `"
b10001101 ]"
b11111100 Z"
b10001111 W"
b1010101 T"
b11100 Q"
b1000 ~
b11000000 8"
b1101111 5"
b1010111 2"
b10001101 /"
b11111100 ,"
b10001111 )"
b1010101 &"
1|
b11100 #"
b1000 P
b11000000 h
b1101111 e
1I
b1010111 b
b10001101 _
b11111100 \
b10001111 Y
b1010101 V
1N
b11100 S
1-
#110000
0-
#115000
1F
1t
1D"
1r"
b111000 S
b10101011 V
b11110 Y
b11111000 \
1J
b11010 _
0I
b10101111 b
b11011110 e
b10000001 h
b1001 P
b111000 #"
b10101011 &"
b11110 )"
b11111000 ,"
1x
b11010 /"
b10101111 2"
b11011110 5"
b10000001 8"
b1001 ~
b111000 Q"
b10101011 T"
b11110 W"
b11111000 Z"
1H"
b11010 ]"
0G"
b10101111 `"
b11011110 c"
b10000001 f"
b1001 N"
b111000 !#
b10101011 $#
b11110 '#
b11111000 *#
1v"
b11010 -#
b10101111 0#
b11011110 3#
b10000001 6#
b1001 |"
1-
#120000
0-
#125000
b1010 |"
b11 6#
b10111101 3#
b1011111 0#
b110100 -#
b11110000 *#
b111100 '#
b1010111 $#
b1110001 !#
b1010 N"
b11 f"
b10111101 c"
1G"
b1011111 `"
b110100 ]"
b11110000 Z"
b111100 W"
b1010111 T"
b1110001 Q"
b1010 ~
b11 8"
b10111101 5"
b1011111 2"
b110100 /"
b11110000 ,"
b111100 )"
b1010111 &"
b1110001 #"
b1010 P
b11 h
b10111101 e
1I
b1011111 b
b110100 _
b11110000 \
b111100 Y
b1010111 V
b1110001 S
1-
#130000
0-
#135000
0F
0t
0D"
0r"
0N
b11100010 S
b10101111 V
b1111001 Y
b11100001 \
b1101000 _
0I
b10111110 b
b1111010 e
b110 h
b1011 P
0|
b11100010 #"
b10101111 &"
b1111001 )"
b11100001 ,"
0x
b1101000 /"
b10111110 2"
b1111010 5"
b110 8"
b1011 ~
0L"
b11100010 Q"
b10101111 T"
b1111001 W"
b11100001 Z"
b1101000 ]"
0G"
b10111110 `"
b1111010 c"
b110 f"
b1011 N"
0z"
b11100010 !#
b10101111 $#
b1111001 '#
b11100001 *#
0v"
b1101000 -#
b10111110 0#
b1111010 3#
b110 6#
b1011 |"
1-
#140000
0-
#145000
b1100 |"
b1100 6#
b11110101 3#
b1111100 0#
b11010000 -#
b11000010 *#
b11110011 '#
b1011111 $#
b11000100 !#
b1100 N"
b1100 f"
b11110101 c"
1G"
b1111100 `"
0H"
b11010000 ]"
b11000010 Z"
b11110011 W"
b1011111 T"
b11000100 Q"
b1100 ~
b1100 8"
b11110101 5"
b1111100 2"
b11010000 /"
b11000010 ,"
b11110011 )"
b1011111 &"
b11000100 #"
b1100 P
b1100 h
b11110101 e
1I
b1111100 b
0J
b11010000 _
b11000010 \
b11110011 Y
b1011111 V
b11000100 S
1-
#150000
0-
#155000
b10001001 S
b10111110 V
b11100111 Y
b10000101 \
b10100000 _
0I
b11111001 b
b11101011 e
b11001 h
b1101 P
b10001001 #"
b10111110 &"
b11100111 )"
b10000101 ,"
b10100000 /"
b11111001 2"
b11101011 5"
b11001 8"
b1101 ~
1L"
b10001001 Q"
b10111110 T"
b11100111 W"
b10000101 Z"
b10100000 ]"
0G"
b11111001 `"
b11101011 c"
b11001 f"
b1101 N"
1z"
b10001001 !#
b10111110 $#
b11100111 '#
b10000101 *#
b10100000 -#
b11111001 0#
b11101011 3#
b11001 6#
b1101 |"
1-
#160000
0-
